MANIFEST.in
elotl/__init__.py
elotl/corpora/__init__.py
elotl/corpora/axolotl.csv
elotl/corpora/kolo.csv
elotl/corpora/tsunkua.csv
elotl/corpus/__init__.py
elotl/huave/__init__.py
elotl/huave/data/__init__.py
elotl/huave/data/huv.mor.att
elotl/huave/data/huv.mor.tsv
elotl/huave/morphology.py
elotl/nahuatl/__init__.py
elotl/nahuatl/config.py
elotl/nahuatl/data/__init__.py
elotl/nahuatl/data/azz.mor.att
elotl/nahuatl/data/azz.mor.tsv
elotl/nahuatl/data/nci.mor.att
elotl/nahuatl/data/nci.mor.tsv
elotl/nahuatl/data/nhi.mor.att
elotl/nahuatl/data/nhi.mor.tsv
elotl/nahuatl/morphology.py
elotl/nahuatl/orthography.py
elotl/otomi/__init__.py
elotl/otomi/config.py
elotl/otomi/data/__init__.py
elotl/otomi/data/ote.mor.att
elotl/otomi/data/ote.mor.tsv
elotl/otomi/morphology.py
elotl/otomi/orthography.py
elotl/utils/__init__.py
elotl/utils/fst/__init__.py
elotl/utils/fst/att/__init__.py
elotl/utils/fst/att/nahuatl/__init__.py
elotl/utils/fst/att/nahuatl/fon-ack.att
elotl/utils/fst/att/nahuatl/fon-ilv.att
elotl/utils/fst/att/nahuatl/fon-inali.att
elotl/utils/fst/att/nahuatl/fon-sep.att
elotl/utils/fst/att/nahuatl/orig-fon.att
elotl/utils/fst/att/otomi/__init__.py
elotl/utils/fst/att/otomi/fon-inali.att
elotl/utils/fst/att/otomi/fon-otq.att
elotl/utils/fst/att/otomi/fon-ots.att
elotl/utils/fst/att/otomi/fon-rfe.att
elotl/utils/fst/att/otomi/orig-fon.att
elotl/utils/fst/attapply.py
elotl/utils/fst/lexc/nahuatl/fon-ack.lexc
elotl/utils/fst/lexc/nahuatl/fon-ilv.lexc
elotl/utils/fst/lexc/nahuatl/fon-inali.lexc
elotl/utils/fst/lexc/nahuatl/fon-sep.lexc
elotl/utils/fst/lexc/nahuatl/orig-fon.lexc
elotl/utils/fst/lexc/otomi/fon-inali.lexc
elotl/utils/fst/lexc/otomi/fon-otq.lexc
elotl/utils/fst/lexc/otomi/fon-ots.lexc
elotl/utils/fst/lexc/otomi/fon-rfe.lexc
elotl/utils/fst/lexc/otomi/orig-fon.lexc
elotl/utils/morphology.py
elotl-0.1.1.dist-info/LICENSE
elotl-0.1.1.dist-info/METADATA
elotl-0.1.1.dist-info/WHEEL
elotl-0.1.1.dist-info/RECORD
