Metadata-Version: 2.1
Name: elotl
Version: 0.1.1
Summary: Python package for Natural Language Processing (NLP), focused on low-resource languages spoken in Mexico.
License: MLP-2.0
Author: Paul Aguilar
Author-email: paul.aguilar.enriquez@hotmail.com
Maintainer: Robert Pugh
Maintainer-email: robertpugh408@gmail.com
Requires-Python: >=3.11,<4.0
Classifier: Development Status :: 4 - Beta
Classifier: Environment :: Console
Classifier: Intended Audience :: Developers
Classifier: Intended Audience :: Education
Classifier: Intended Audience :: Science/Research
Classifier: License :: OSI Approved :: Mozilla Public License 2.0 (MPL 2.0)
Classifier: License :: Other/Proprietary License
Classifier: Natural Language :: Spanish
Classifier: Operating System :: OS Independent
Classifier: Programming Language :: Python :: 3
Classifier: Programming Language :: Python :: 3.11
Classifier: Programming Language :: Python :: 3.12
Classifier: Programming Language :: Python :: 3.13
Classifier: Topic :: Scientific/Engineering :: Artificial Intelligence
Classifier: Topic :: Utilities
